{"type":"PR","pr":{"number":55,"head":"cc6b2d917abec31b848c70683bf6b589aaeb1827"},"user":"ricardo.bonis","status":"pending_publish","branch":"cms/2018-10-10-​​cinq-leçons-de-com-du-président-macron","collection":"news_french","title":"​​Cinq leçons de com du Président Macron","description":"No Description!","objects":{"entry":{"path":"content/news/2018-10-10-​​cinq-leçons-de-com-du-président-macron.fr.md","sha":"25001bc929fcab192ddefa627894be907217111c"},"files":[]},"timeStamp":"2018-10-10T18:22:50.254Z"}